mnm/__init__.py
mnm/_internal_utils.py
mnm/global_functions.py
mnm/header_mocking.py
mnm/mixed.py
mnm/socket_fragmentation.py
mnm/wrapper.py
mnm/examples/mixed_options.py
mnm/examples/mixed_simple.py
mnm/examples/ssl_test.py
mnm/examples/with_pattern.py
mnm-0.3.1.dist-info/LICENSE
mnm-0.3.1.dist-info/METADATA
mnm-0.3.1.dist-info/WHEEL
mnm-0.3.1.dist-info/top_level.txt
mnm-0.3.1.dist-info/RECORD
