Metadata-Version: 2.1
Name: mnm
Version: 0.3.1
Summary: A simple python library for pentesting firewall protected webapp
Author-email: ohk990102 <ohk990102@gmail.com>
Project-URL: Homepage, https://github.com/ohk990102/mnm
Project-URL: Bug Tracker, https://github.com/ohk990102/mnm/issues
Classifier: Programming Language :: Python :: 3
Classifier: License :: OSI Approved :: MIT License
Classifier: Operating System :: POSIX :: Linux
License-File: LICENSE
Requires-Dist: requests >=2.26.0
